{
  "_class": "bitmap",
  "booleanOperation": -1,
  "clippingMask": "{{0, 0}, {1, 1}}",
  "clippingMaskMode": 0,
  "do_objectID": "3CEA8B52-E2C6-4B44-8748-87D8281370AE",
  "exportOptions": {
    "_class": "exportOptions",
    "do_objectID": "62F8261B-450D-4D5F-86CC-ACD7D57CDF3E",
    "exportFormats": [
    ],
    "includedLayerIds": [
    ],
    "layerOptions": 0,
    "shouldTrim": false
  },
  "fillReplacesImage": false,
  "frame": {
    "_class": "rect",
    "constrainProportions": true,
    "do_objectID": "8494291A-D232-4C3A-856F-181B3B1D0C44",
    "height": 30,
    "width": 30,
    "x": 803,
    "y": 2014
  },
  "hasClippingMask": false,
  "image": {
    "_class": "MSJSONFileReference",
    "_ref": "images/302834b7dcab37ceb6c4a852fc94c18bacb15ada.png",
    "_ref_class": "MSImageData"
  },
  "intendedDPI": 72,
  "isFixedToViewport": false,
  "isFlippedHorizontal": false,
  "isFlippedVertical": false,
  "isLocked": false,
  "isVisible": true,
  "layerListExpandedType": 0,
  "name": "zoom-logo_0",
  "nameIsFixed": false,
  "resizingConstraint": 63,
  "resizingType": 0,
  "rotation": 0,
  "shouldBreakMaskChain": false,
  "style": {
    "_class": "style",
    "do_objectID": "9CF24783-6CA4-4659-9185-F9639724AF39",
    "endMarkerType": 0,
    "miterLimit": 10,
    "startMarkerType": 0,
    "windingRule": 1
  }
}